MANIFEST.in
setup.cfg
setup.py
bkoauth/__init__.py
bkoauth/admin.py
bkoauth/client.py
bkoauth/decorators.py
bkoauth/django_conf.py
bkoauth/exceptions.py
bkoauth/jwt_client.py
bkoauth/models.py
bkoauth/signals.py
bkoauth/utils.py
bkoauth.egg-info/PKG-INFO
bkoauth.egg-info/SOURCES.txt
bkoauth.egg-info/dependency_links.txt
bkoauth.egg-info/not-zip-safe
bkoauth.egg-info/requires.txt
bkoauth.egg-info/top_level.txt
bkoauth/migrations/0001_initial.py
bkoauth/migrations/0002_auto_20161117_1754.py
bkoauth/migrations/0003_auto_20170224_0814.py
bkoauth/migrations/__init__.py
bkoauth/south_migrations/0001_initial.py
bkoauth/south_migrations/0002_auto.py
bkoauth/south_migrations/__init__.py